MANIFEST.in
setup.py
docs/CONTRIBUTORS.txt
docs/HISTORY.txt
docs/LICENSE.ZPL
docs/LICENSE.txt
docs/README.txt
src/ztfy/__init__.py
src/ztfy.lock.egg-info/PKG-INFO
src/ztfy.lock.egg-info/SOURCES.txt
src/ztfy.lock.egg-info/dependency_links.txt
src/ztfy.lock.egg-info/namespace_packages.txt
src/ztfy.lock.egg-info/not-zip-safe
src/ztfy.lock.egg-info/requires.txt
src/ztfy.lock.egg-info/top_level.txt
src/ztfy/lock/__init__.py
src/ztfy/lock/configure.zcml
src/ztfy/lock/database.py
src/ztfy/lock/helper.py
src/ztfy/lock/interfaces.py
src/ztfy/lock/utility.py
src/ztfy/lock/browser/__init__.py
src/ztfy/lock/browser/configure.zcml
src/ztfy/lock/browser/utility.py
src/ztfy/lock/doctests/README.txt
src/ztfy/lock/locales/ztfy.lock.pot
src/ztfy/lock/locales/en/LC_MESSAGES/ztfy.lock.mo
src/ztfy/lock/locales/en/LC_MESSAGES/ztfy.lock.po
src/ztfy/lock/locales/fr/LC_MESSAGES/ztfy.lock.mo
src/ztfy/lock/locales/fr/LC_MESSAGES/ztfy.lock.po
src/ztfy/lock/tests/__init__.py
src/ztfy/lock/tests/test_docs.py
src/ztfy/lock/tests/test_docstrings.py