Metadata-Version: 1.1
Name: ztfy.lock
Version: 0.1.0
Summary: ZTFY interfaces and utilities for locks handling
Home-page: http://www.ztfy.org
Author: Thierry Florac
Author-email: tflorac@ulthar.net
License: ZPL
Platform: UNKNOWN
Classifier: Programming Language :: Python
